ipyblender_experimental/.DS_Store
ipyblender_experimental/__init__.py
ipyblender_experimental/render_to_gltf_model.py
ipyblender_experimental/render_to_image.py
ipyblender_experimental/static/widget.js
ipyblender_experimental/static/widget2.js
ipyblender_experimental-0.2.0.dist-info/METADATA
ipyblender_experimental-0.2.0.dist-info/WHEEL
ipyblender_experimental-0.2.0.dist-info/licenses/LICENSE
ipyblender_experimental-0.2.0.dist-info/RECORD
