Metadata-Version: 2.1
Name: ipyblender_experimental
Version: 0.2.0
License-File: LICENSE
Requires-Python: ~=3.10.0
Requires-Dist: anywidget
Requires-Dist: bpy
Requires-Dist: ipykernel
Requires-Dist: watchfiles
